mastro-fs/__init__.py
mastro-fs/client.py
mastro_fs/__init__.py
mastro_fs/client.py
mastro_fs/dto.py
mastro_fs-0.1.0.dist-info/METADATA
mastro_fs-0.1.0.dist-info/WHEEL
mastro_fs-0.1.0.dist-info/top_level.txt
mastro_fs-0.1.0.dist-info/RECORD
