Metadata-Version: 2.1
Name: mastro-fs
Version: 0.1.0
Summary: A Python library to interact with Mastro feature stores
Home-page: https://github.com/datamillcloud/mastro
Author: pilillo
License: Apache License 2.0
Keywords: mastro,featurestore,mlops
Platform: UNKNOWN
